megan_global_explanations/VERSION
megan_global_explanations/__init__.py
megan_global_explanations/cli.py
megan_global_explanations/data.py
megan_global_explanations/dbadv.py
megan_global_explanations/deep_ect.py
megan_global_explanations/examples/00_concept_report.py
megan_global_explanations/examples/01_saving_loading.py
megan_global_explanations/examples/concept_report.pdf
megan_global_explanations/experiments/assets/concepts/aqsoldb/000/metadata.json
megan_global_explanations/experiments/assets/concepts/aqsoldb/001/metadata.json
megan_global_explanations/experiments/assets/concepts/aqsoldb/002/metadata.json
megan_global_explanations/experiments/assets/concepts/aqsoldb/003/metadata.json
megan_global_explanations/experiments/assets/concepts/aqsoldb/004/metadata.json
megan_global_explanations/experiments/assets/concepts/aqsoldb/005/metadata.json
megan_global_explanations/experiments/assets/concepts/aqsoldb/006/metadata.json
megan_global_explanations/experiments/assets/concepts/aqsoldb/007/metadata.json
megan_global_explanations/experiments/assets/concepts/aqsoldb/008/metadata.json
megan_global_explanations/experiments/assets/concepts/aqsoldb/009/metadata.json
megan_global_explanations/experiments/assets/concepts/aqsoldb/010/metadata.json
megan_global_explanations/experiments/assets/concepts/aqsoldb/011/metadata.json
megan_global_explanations/experiments/assets/concepts/aqsoldb/012/metadata.json
megan_global_explanations/experiments/assets/concepts/aqsoldb/013/metadata.json
megan_global_explanations/experiments/assets/concepts/aqsoldb/014/metadata.json
megan_global_explanations/experiments/assets/concepts/aqsoldb/015/metadata.json
megan_global_explanations/experiments/assets/concepts/aqsoldb/016/metadata.json
megan_global_explanations/experiments/assets/concepts/aqsoldb/017/metadata.json
megan_global_explanations/experiments/assets/concepts/aqsoldb/018/metadata.json
megan_global_explanations/experiments/assets/concepts/aqsoldb/019/metadata.json
megan_global_explanations-0.2.2.dist-info/LICENSE
megan_global_explanations-0.2.2.dist-info/METADATA
megan_global_explanations-0.2.2.dist-info/WHEEL
megan_global_explanations-0.2.2.dist-info/entry_points.txt
megan_global_explanations-0.2.2.dist-info/RECORD
