Metadata-Version: 2.1
Name: megan-global-explanations
Version: 0.2.2
Summary: Insert Description
License: MIT
Author: Jonas Teufel
Author-email: jonseb1998@gmail.com
Maintainer: Jonas Teufel
Maintainer-email: jonseb1998@gmail.com
Requires-Python: >=3.8.0,<4.0
Classifier: License :: OSI Approved :: MIT License
Classifier: Programming Language :: Python :: 3
Classifier: Programming Language :: Python :: 3.8
Classifier: Programming Language :: Python :: 3.9
Classifier: Programming Language :: Python :: 3.10
Classifier: Programming Language :: Python :: 3.11
Requires-Dist: click (>=7.1.2)
Requires-Dist: graph-attention-student (>=0.12.0)
Requires-Dist: hdbscan (>=0.8.0)
Requires-Dist: jinja2 (>=3.0.3)
Requires-Dist: matplotlib (>=3.5.3)
Requires-Dist: numpy (>=1.23.2)
Requires-Dist: poetry-bumpversion (>=0.3.0)
Requires-Dist: pycomex (>=0.9.2)
Requires-Dist: python-decouple (>=3.6)
Requires-Dist: umap-learn (>=0.5.3)
Requires-Dist: visual-graph-datasets (>=0.15.1)
Requires-Dist: weasyprint (>=61.1)
